__init__.py
flask_problem_details.py
flask_problem_details-3.0.1.dist-info/licenses/LICENSE
flask_problem_details-3.0.1.dist-info/METADATA
flask_problem_details-3.0.1.dist-info/WHEEL
flask_problem_details-3.0.1.dist-info/top_level.txt
flask_problem_details-3.0.1.dist-info/RECORD
