Metadata-Version: 2.4
Name: flask-problem-details
Version: 3.0.1
Summary: A package that implements problem details errors in Flask App
Author: mikeymat
Project-URL: Homepage, https://github.com/mikeymat/flask-problem-details
Project-URL: Issues, https://github.com/mikeymat/flask-problem-details/issues
Classifier: Programming Language :: Python :: 3
Classifier: License :: OSI Approved :: MIT License
Classifier: Operating System :: OS Independent
Requires-Python: >=3.10
License-File: LICENSE
Requires-Dist: flask-openapi3<5.0.0,>=4.0.0
Requires-Dist: pydantic<3.0.0,>=2.10.4
Dynamic: license-file
